mapping_to_namedtuple/__init__.py
mapping_to_namedtuple/mapping_to_namedtuple.py
mapping_to_namedtuple/tests/__init__.py
mapping_to_namedtuple/tests/test_mapping_to_namedtuple.py
mapping_to_namedtuple-0.1.dist-info/LICENSE
mapping_to_namedtuple-0.1.dist-info/METADATA
mapping_to_namedtuple-0.1.dist-info/WHEEL
mapping_to_namedtuple-0.1.dist-info/top_level.txt
mapping_to_namedtuple-0.1.dist-info/RECORD
