Metadata-Version: 2.1
Name: mapping-to-namedtuple
Version: 0.1
Summary: Converts Python Mapping to namedtuple recursively
Home-page: https://github.com/datalyticsbe/mapping_to_namedtuple/
Author: Datalytics BVBA
Author-email: datalyticsbe@gmail.com
License: MIT
Keywords: mapping,dict,namedtuple,convert
Platform: UNKNOWN
Classifier: Development Status :: 3 - Alpha
Classifier: Intended Audience :: Developers
Classifier: Programming Language :: Python :: 3
Classifier: Programming Language :: Python :: 3.6
Classifier: Programming Language :: Python :: 3.7
Requires-Python: >=3.6
